PyMyGekko/__about__.py
PyMyGekko/__init__.py
PyMyGekko/api_var_demo_data.json
PyMyGekko/api_var_status_demo_data.json
PyMyGekko/data_provider.py
PyMyGekko/resources/AccessDoors.py
PyMyGekko/resources/Actions.py
PyMyGekko/resources/AlarmsLogics.py
PyMyGekko/resources/Blinds.py
PyMyGekko/resources/Cams.py
PyMyGekko/resources/DoorInterComs.py
PyMyGekko/resources/EnergyCosts.py
PyMyGekko/resources/HotWaterSystems.py
PyMyGekko/resources/Lights.py
PyMyGekko/resources/Loads.py
PyMyGekko/resources/Meteo.py
PyMyGekko/resources/RoomTemps.py
PyMyGekko/resources/Vents.py
PyMyGekko/resources/__init__.py
pymygekko-1.5.1.dist-info/METADATA
pymygekko-1.5.1.dist-info/WHEEL
pymygekko-1.5.1.dist-info/licenses/LICENSE
pymygekko-1.5.1.dist-info/RECORD
