Metadata-Version: 2.4
Name: PyMyGekko
Version: 1.5.1
Summary: Python Library to access the myGEKKO Query API.
Project-URL: Documentation, https://github.com/StephanU/#readme
Project-URL: Issues, https://github.com/StephanU/PyMyGekko/issues
Project-URL: Source, https://github.com/StephanU/PyMyGekko
Author-email: Stephan Uhle <stephanu@gmx.net>
License-Expression: MIT
License-File: LICENSE
Keywords: mygekko
Classifier: Development Status :: 5 - Production/Stable
Classifier: Intended Audience :: Developers
Classifier: Programming Language :: Python
Classifier: Programming Language :: Python :: 3.12
Classifier: Programming Language :: Python :: 3.13
Classifier: Programming Language :: Python :: Implementation :: CPython
Classifier: Programming Language :: Python :: Implementation :: PyPy
Requires-Python: >=3.12
Requires-Dist: aiohttp>=3.8
